pyta/__init__.py
pyta/smoothing_cpp.cp313-win_amd64.pyd
pyta/smoothing_cpp.pyi
pyta/calculations/__init__.py
pyta/calculations/smoothings.py
pyta/chart/__init__.py
pyta/chart/central_draw.py
pyta/chart/chart.py
pyta/config/__init__.py
pyta/config/base.py
pyta/config/dev.py
pyta/config/loader.py
pyta/config/prod.py
pyta/excep/__init__.py
pyta/excep/envs/missing_keys.py
pyta/excep/indicators/line_not_supported.py
pyta/indicator/__init__.py
pyta/indicator/base.py
pyta/indicator/macd.py
pyta/indicator/rsi.py
pyta/infras/__init__.py
pyta/infras/mt5_manager.py
pyta/models/price.py
pyta/strategy/price/__init__.py
pyta/strategy/price/base.py
pyta/strategy/price/close.py
pyta_trader-0.1.3.dist-info/licenses/LICENSE
pyta_trader-0.1.3.dist-info/METADATA
pyta_trader-0.1.3.dist-info/WHEEL
pyta_trader-0.1.3.dist-info/top_level.txt
pyta_trader-0.1.3.dist-info/RECORD
