Metadata-Version: 2.4
Name: pyta_trader
Version: 0.1.3
Summary: A Python-based trading framework integrating with MetaTrader 5 (MT5).
Author-email: Lê Phạm Hùng Cường <cuongdayne17@gmail.com>, Nguyễn Phước Anh Dũng <anhdungnguyen955@gmail.com>, Lê Quốc Anh <Reina.Maccredy@outlook.com>
License: This work is licensed under the Creative Commons Attribution-NonCommercial 4.0 International License.
Project-URL: HomePage, https://github.com/ticuong78/pyta-trader
Project-URL: Issue, https://github.com/ticuong78/pyta-trader/issues
Keywords: Meta Trader 5,trading platform,integrating
Classifier: Programming Language :: Python :: 3.13
Classifier: Programming Language :: C++
Classifier: Topic :: Utilities
Requires-Python: >=3.13
License-File: LICENSE
Requires-Dist: MetaTrader5==5.0.5050
Requires-Dist: numpy==2.2.6
Requires-Dist: typing_extensions==4.13.2
Requires-Dist: pydantic==2.11.5
Provides-Extra: dev
Requires-Dist: pytest==8.3.5; extra == "dev"
Requires-Dist: twine==6.1.0; extra == "dev"
Requires-Dist: readme_renderer==44.0; extra == "dev"
Requires-Dist: setuptools==80.9.0; extra == "dev"
Requires-Dist: virtualenv==20.30.0; extra == "dev"
Requires-Dist: build==1.2.2; extra == "dev"
Dynamic: license-file
